{
    "train_1": {
        "train_id": 1,
        "commanded_speed": 0.0,
        "commanded_authority": 0.0,
        "speed_limit": 0.0,
        "train_velocity": 0.0,
        "next_stop": "",
        "station_side": "",
        "manual_mode": false,
        "driver_velocity": 0.0,
        "service_brake": false,
        "emergency_brake": false,
        "kp": 1500.0,
        "ki": 50.0,
        "power_command": 0.0,
        "current_station": ""
    },
    "train_2": {
        "train_id": 2,
        "commanded_speed": 0.0,
        "commanded_authority": 0.0,
        "speed_limit": 0.0,
        "train_velocity": 0.0,
        "next_stop": "",
        "station_side": "",
        "manual_mode": false,
        "driver_velocity": 0.0,
        "service_brake": false,
        "emergency_brake": false,
        "kp": 1500.0,
        "ki": 50.0,
        "power_command": 0.0,
        "current_station": ""
    }
}